pyrsolace/__init__.py
pyrsolace/__init__.pyi
pyrsolace/py.typed
pyrsolace/pyrsolace.abi3.so
pyrsolace-0.3.9.dist-info/METADATA
pyrsolace-0.3.9.dist-info/WHEEL
pyrsolace-0.3.9.dist-info/RECORD
