Metadata-Version: 2.4
Name: pyrsolace
Version: 0.3.9
Classifier: Programming Language :: Rust
Classifier: Programming Language :: Python :: Implementation :: CPython
Classifier: Programming Language :: Python :: Implementation :: PyPy
Summary: Python bindings for rsolace
Keywords: solace,python,rsolace,rust
Author-email: yvictor <yvictor3141@gmail.com>
Requires-Python: >=3.7
